src/__init__.py
src/gugu_relay.py
src/gugurelay/__init__.py
src/gugurelay/device/__init__.py
src/gugurelay/device/device_base.py
src/gugurelay/device/device_can.py
src/gugurelay/device/device_manager.py
src/gugurelay/device/device_xcp.py
src/gugurelay/pythoncan/__init__.py
src/gugurelay/usbtool/__init__.py
src/gugurelay/usbtool/usb_manager.py
src/gugurelay/usbtool/usb_trigger.py
src/gugurelay/utils/__init__.py
src/gugurelay/utils/error.py
src/gugurelay/utils/util.py
tests/__init__.py
tests/test_python-can.py
tests/test_relay.py
tests/test_send.py
gugurelay-0.2.dist-info/LICENSE
gugurelay-0.2.dist-info/METADATA
gugurelay-0.2.dist-info/WHEEL
gugurelay-0.2.dist-info/top_level.txt
gugurelay-0.2.dist-info/RECORD
