Metadata-Version: 2.1
Name: gugurelay
Version: 0.2
Summary: A short description of the project
Author: Your Name
Author-email: your.email@example.com
Classifier: Programming Language :: Python :: 3
Classifier: License :: OSI Approved :: MIT License
Classifier: Operating System :: OS Independent
License-File: LICENSE
Requires-Dist: python-can
Requires-Dist: python-can[canalystii]
Requires-Dist: pywin32
Requires-Dist: pywin32-ctypes
